libNMF-0.1.2.dist-info/METADATA
libNMF-0.1.2.dist-info/RECORD
libNMF-0.1.2.dist-info/WHEEL
libNMF-0.1.2.dist-info/top_level.txt
libnmf/__init__.py
libnmf/alsnmf.py
libnmf/fpdnmf.py
libnmf/gnmf.py
libnmf/knmf.py
libnmf/nmf.py
libnmf/nmfbase.py
libnmf/pnmf.py
libnmf/kernels/__init__.py
libnmf/kernels/rbf.py
tests/__init__.py
tests/test_libnmf.py
