Metadata-Version: 2.1
Name: libNMF
Version: 0.1.2
Summary: Optimization and Regularization variants of NMF
Home-page: https://github.com/satwik77/libnmf/
Author: Satwik Bhattamishra
Author-email: satwik55@gmail.com
License: MIT
Platform: UNKNOWN
Classifier: Development Status :: 2 - Pre-Alpha
Classifier: License :: OSI Approved :: MIT License
Classifier: Programming Language :: Python
Classifier: Programming Language :: Python :: 2
Classifier: Programming Language :: Python :: 2.7
Classifier: Programming Language :: Python :: 3
Classifier: Programming Language :: Python :: 3.5
Requires-Dist: numpy (>=1.1.0)
Requires-Dist: scipy (>=1.1.0)
Requires-Dist: cvxopt (>=1.2.0)
